odoo/addons/account_due_list_payment/__init__.py
odoo/addons/account_due_list_payment/__manifest__.py
odoo/addons/account_due_list_payment/i18n/account_due_list_payment.pot
odoo/addons/account_due_list_payment/i18n/es.po
odoo/addons/account_due_list_payment/i18n/it.po
odoo/addons/account_due_list_payment/models/__init__.py
odoo/addons/account_due_list_payment/models/account_move_line.py
odoo/addons/account_due_list_payment/static/description/icon.png
odoo/addons/account_due_list_payment/tests/__init__.py
odoo/addons/account_due_list_payment/tests/test_action_register_payment.py
odoo/addons/account_due_list_payment/views/account_move_line.xml
odoo14_addon_account_due_list_payment-14.0.1.0.1.dist-info/METADATA
odoo14_addon_account_due_list_payment-14.0.1.0.1.dist-info/WHEEL
odoo14_addon_account_due_list_payment-14.0.1.0.1.dist-info/top_level.txt
odoo14_addon_account_due_list_payment-14.0.1.0.1.dist-info/RECORD
